Metadata-Version: 2.1
Name: napari-microtubule-analyzer
Version: 0.0.1a3
Summary: A plugin to analyze microtubule organization
Home-page: https://github.com/krentzd/napari-microtubule-analyzer
Author: Daniel Krentzel
Author-email: dkrentzel@pm.me
License: MIT
Project-URL: Bug Tracker, https://github.com/krentzd/napari-microtubule-analyzer/issues
Project-URL: Documentation, https://github.com/krentzd/napari-microtubule-analyzer#README.md
Project-URL: Source Code, https://github.com/krentzd/napari-microtubule-analyzer
Project-URL: User Support, https://github.com/krentzd/napari-microtubule-analyzer/issues
Classifier: Development Status :: 2 - Pre-Alpha
Classifier: Framework :: napari
Classifier: Intended Audience :: Developers
Classifier: License :: OSI Approved :: MIT License
Classifier: Operating System :: OS Independent
Classifier: Programming Language :: Python
Classifier: Programming Language :: Python :: 3
Classifier: Programming Language :: Python :: 3 :: Only
Classifier: Programming Language :: Python :: 3.8
Classifier: Programming Language :: Python :: 3.9
Classifier: Programming Language :: Python :: 3.10
Classifier: Topic :: Scientific/Engineering :: Image Processing
Requires-Python: >=3.8
Provides-Extra: testing
License-File: LICENSE
